LICENSE
README.md
setup.cfg
setup.py
yano/__init__.py
yano.egg-info/PKG-INFO
yano.egg-info/SOURCES.txt
yano.egg-info/dependency_links.txt
yano.egg-info/requires.txt
yano.egg-info/top_level.txt
yano/const/__init__.py
yano/data/__init__.py
yano/data/dataset.py
yano/data/iterate.py
yano/data/loaddata.py
yano/data/timestamp.py
yano/ensemble/__init__.py
yano/ensemble/dean.py
yano/ensemble/densedrop.py
yano/ensemble/genmat.py
yano/ensemble/randnet.py
yano/helper/__init__.py
yano/helper/helper.py
yano/iter/__init__.py
yano/iter/handler.py
yano/iter/helper.py
yano/iter/iterators.py
yano/logging/__init__.py
yano/logging/logger.py
yano/quick/__init__.py
yano/quick/qcardio.py
yano/stats/__init__.py
yano/stats/likelihood.py
yano/stats/methods.py
yano/stats/stats.py
yano/symbols/__init__.py
yano/symbols/metalogic.py
yano/symbols/symbols.py
yano/utils/__init__.py
yano/utils/modify.py
yano/utils/utils.py
yano/vis/__init__.py
yano/vis/altitude.py
yano/vis/hist.py
yano/vis/linedraw.py
yano/vis/projector.py
yano/vis/reducedraw.py